print_yaml/__init__.py
print_yaml/main.py
print_yaml-0.1.0.dist-info/entry_points.txt
print_yaml-0.1.0.dist-info/WHEEL
print_yaml-0.1.0.dist-info/METADATA
print_yaml-0.1.0.dist-info/RECORD
