Metadata-Version: 2.1
Name: print-yaml
Version: 0.1.0
Summary: 
Author: heumsi
Author-email: heumsi@naver.com
Requires-Python: >=3.10,<4.0
Classifier: Programming Language :: Python :: 3
Classifier: Programming Language :: Python :: 3.10
Requires-Dist: PyYAML (>=6.0,<7.0)
Requires-Dist: typer[all] (>=0.6.1,<0.7.0)
